odoo/addons/partner_code_program_account/README.rst
odoo/addons/partner_code_program_account/__init__.py
odoo/addons/partner_code_program_account/__manifest__.py
odoo/addons/partner_code_program_account/i18n/es.po
odoo/addons/partner_code_program_account/models/__init__.py
odoo/addons/partner_code_program_account/models/account_invoice_report.py
odoo/addons/partner_code_program_account/models/account_move.py
odoo/addons/partner_code_program_account/readme/CONFIGURE.md
odoo/addons/partner_code_program_account/readme/CONTRIBUTORS.md
odoo/addons/partner_code_program_account/readme/DESCRIPTION.md
odoo/addons/partner_code_program_account/readme/INSTALL.md
odoo/addons/partner_code_program_account/readme/USAGE.md
odoo/addons/partner_code_program_account/static/description/icon.png
odoo/addons/partner_code_program_account/static/description/index.html
odoo/addons/partner_code_program_account/tests/__init__.py
odoo/addons/partner_code_program_account/tests/test_partner_code_program_account.py
odoo/addons/partner_code_program_account/views/account_invoice_report.xml
odoo/addons/partner_code_program_account/views/account_move.xml
odoo_addon_partner_code_program_account-18.0.1.0.0.1.dist-info/METADATA
odoo_addon_partner_code_program_account-18.0.1.0.0.1.dist-info/WHEEL
odoo_addon_partner_code_program_account-18.0.1.0.0.1.dist-info/top_level.txt
odoo_addon_partner_code_program_account-18.0.1.0.0.1.dist-info/RECORD
